kelompok2tubes3342331018/__init__.py
kelompok2tubes3342331018/kelompok2.py
kelompok2tubes3342331018-0.1.dist-info/LICENSE
kelompok2tubes3342331018-0.1.dist-info/METADATA
kelompok2tubes3342331018-0.1.dist-info/WHEEL
kelompok2tubes3342331018-0.1.dist-info/top_level.txt
kelompok2tubes3342331018-0.1.dist-info/RECORD
